{
  "required": true,
  "package": "com.yungnickyoung.minecraft.betterjungletemples.mixin",
  "compatibilityLevel": "JAVA_17",
  "refmap": "betterjungletemples.refmap.json",
  "mixins": [
    "DisableVanillaJungleTempleMixin",
    "LocateVanillaJungleTempleCommandMixin",
    "NoVinesInTemplesMixin",
    "StructureTemplateMixin",
    "accessor.ChunkGeneratorStructureStateAccessor",
    "accessor.StructureManagerAccessor",
    "accessor.StructureProcessorAccessor",
    "accessor.WorldGenRegionAccessor"
  ],
  "injectors": {
    "defaultRequire": 1
  },
  "minVersion": "0.8"
}
